[
    {
        "content": [
            {
                "x": 496.67065868263467,
                "y": 854.6227544910179
            },
            {
                "x": 3680.1916167664667,
                "y": 1054.6706586826347
            },
            {
                "x": 3611.209580838323,
                "y": 1478.9101796407185
            },
            {
                "x": 558.754491017964,
                "y": 1116.754491017964
            }
        ],
        "rectMask": {
            "xMin": 496.67065868263467,
            "yMin": 854.6227544910179,
            "width": 3183.5209580838323,
            "height": 624.2874251497005
        },
        "labels": {
            "labelName": "unnamed",
            "labelColor": "red",
            "labelColorRGB": "255,0,0",
            "visibility": false
        },
        "labelLocation": {
            "x": 2088.431137724551,
            "y": 1166.7664670658683
        },
        "contentType": "polygon"
    }
]