[
    {
        "content": [
            {
                "x": 0,
                "y": 467.1140939597316
            },
            {
                "x": 16.778523489932734,
                "y": 1191.9463087248323
            },
            {
                "x": 3733.557046979866,
                "y": 841.6107382550335
            },
            {
                "x": 3785.9060402684563,
                "y": 422.81879194630875
            }
        ],
        "rectMask": {
            "xMin": 0,
            "yMin": 422.81879194630875,
            "width": 3785.9060402684563,
            "height": 769.1275167785235
        },
        "labels": {
            "labelName": "unnamed",
            "labelColor": "red",
            "labelColorRGB": "255,0,0",
            "visibility": false
        },
        "labelLocation": {
            "x": 1892.9530201342282,
            "y": 807.3825503355705
        },
        "contentType": "polygon"
    }
]