[
    {
        "content": [
            {
                "x": 42.0353982300885,
                "y": 1707.9646017699115
            },
            {
                "x": 3320.796460176991,
                "y": 1203.5398230088495
            },
            {
                "x": 3342.9203539823006,
                "y": 1539.8230088495575
            },
            {
                "x": 117.2566371681416,
                "y": 2247.787610619469
            }
        ],
        "rectMask": {
            "xMin": 42.0353982300885,
            "yMin": 1203.5398230088495,
            "width": 3300.884955752212,
            "height": 1044.2477876106195
        },
        "labels": {
            "labelName": "unnamed",
            "labelColor": "red",
            "labelColorRGB": "255,0,0",
            "visibility": false
        },
        "labelLocation": {
            "x": 1692.4778761061946,
            "y": 1725.6637168141592
        },
        "contentType": "polygon"
    }
]