[
    {
        "content": [
            {
                "x": 0,
                "y": 1328.8590604026847
            },
            {
                "x": 0.6711409395971628,
                "y": 1940.9395973154362
            },
            {
                "x": 3999.9999999999995,
                "y": 2037.5838926174497
            },
            {
                "x": 3995.3020134228186,
                "y": 1159.731543624161
            }
        ],
        "rectMask": {
            "xMin": 0,
            "yMin": 1159.731543624161,
            "width": 3999.9999999999995,
            "height": 877.8523489932886
        },
        "labels": {
            "labelName": "unnamed",
            "labelColor": "red",
            "labelColorRGB": "255,0,0",
            "visibility": false
        },
        "labelLocation": {
            "x": 1999.9999999999998,
            "y": 1598.6577181208054
        },
        "contentType": "polygon"
    }
]