[
    {
        "content": [
            {
                "x": 81.85840707964601,
                "y": 1194.6902654867256
            },
            {
                "x": 3537.6106194690265,
                "y": 1168.141592920354
            },
            {
                "x": 3559.734513274336,
                "y": 1845.132743362832
            },
            {
                "x": 6.6371681415929205,
                "y": 1880.5309734513273
            }
        ],
        "rectMask": {
            "xMin": 6.6371681415929205,
            "yMin": 1168.141592920354,
            "width": 3553.097345132743,
            "height": 712.3893805309734
        },
        "labels": {
            "labelName": "unnamed",
            "labelColor": "red",
            "labelColorRGB": "255,0,0",
            "visibility": false
        },
        "labelLocation": {
            "x": 1783.1858407079644,
            "y": 1524.3362831858408
        },
        "contentType": "polygon"
    }
]