[
    {
        "content": [
            {
                "x": 169.66966966966967,
                "y": 1339.3393393393392
            },
            {
                "x": 536.036036036036,
                "y": 1321.3213213213212
            },
            {
                "x": 524.024024024024,
                "y": 3597.5975975975975
            },
            {
                "x": 199.6996996996997,
                "y": 3627.6276276276276
            }
        ],
        "rectMask": {
            "xMin": 169.66966966966967,
            "yMin": 1321.3213213213212,
            "width": 366.3663663663663,
            "height": 2306.3063063063064
        },
        "labels": {
            "labelName": "unnamed",
            "labelColor": "red",
            "labelColorRGB": "255,0,0",
            "visibility": false
        },
        "labelLocation": {
            "x": 352.85285285285283,
            "y": 2474.4744744744744
        },
        "contentType": "polygon"
    },
    {
        "content": [
            {
                "x": 560.06006006006,
                "y": 1297.2972972972973
            },
            {
                "x": 890.3903903903904,
                "y": 1303.3033033033032
            },
            {
                "x": 824.3243243243243,
                "y": 3549.5495495495493
            },
            {
                "x": 554.0540540540541,
                "y": 3591.591591591591
            }
        ],
        "rectMask": {
            "xMin": 554.0540540540541,
            "yMin": 1297.2972972972973,
            "width": 336.33633633633633,
            "height": 2294.294294294294
        },
        "labels": {
            "labelName": "unnamed",
            "labelColor": "red",
            "labelColorRGB": "255,0,0",
            "visibility": false
        },
        "labelLocation": {
            "x": 722.2222222222222,
            "y": 2444.4444444444443
        },
        "contentType": "polygon"
    },
    {
        "content": [
            {
                "x": 920.4204204204203,
                "y": 1261.261261261261
            },
            {
                "x": 1274.7747747747746,
                "y": 1279.2792792792793
            },
            {
                "x": 1136.6366366366365,
                "y": 3579.5795795795793
            },
            {
                "x": 860.3603603603603,
                "y": 3579.5795795795793
            }
        ],
        "rectMask": {
            "xMin": 860.3603603603603,
            "yMin": 1261.261261261261,
            "width": 414.4144144144144,
            "height": 2318.3183183183182
        },
        "labels": {
            "labelName": "unnamed",
            "labelColor": "red",
            "labelColorRGB": "255,0,0",
            "visibility": false
        },
        "labelLocation": {
            "x": 1067.5675675675675,
            "y": 2420.42042042042
        },
        "contentType": "polygon"
    },
    {
        "content": [
            {
                "x": 1292.7927927927926,
                "y": 1243.2432432432431
            },
            {
                "x": 1659.1591591591591,
                "y": 1231.2312312312313
            },
            {
                "x": 1472.972972972973,
                "y": 3597.5975975975975
            },
            {
                "x": 1178.6786786786786,
                "y": 3573.5735735735734
            }
        ],
        "rectMask": {
            "xMin": 1178.6786786786786,
            "yMin": 1231.2312312312313,
            "width": 480.4804804804805,
            "height": 2366.366366366366
        },
        "labels": {
            "labelName": "unnamed",
            "labelColor": "red",
            "labelColorRGB": "255,0,0",
            "visibility": false
        },
        "labelLocation": {
            "x": 1418.9189189189187,
            "y": 2414.4144144144143
        },
        "contentType": "polygon"
    },
    {
        "content": [
            {
                "x": 1677.177177177177,
                "y": 1225.2252252252251
            },
            {
                "x": 2031.5315315315315,
                "y": 1219.2192192192192
            },
            {
                "x": 1785.2852852852852,
                "y": 3567.5675675675675
            },
            {
                "x": 1490.990990990991,
                "y": 3585.5855855855852
            }
        ],
        "rectMask": {
            "xMin": 1490.990990990991,
            "yMin": 1219.2192192192192,
            "width": 540.5405405405405,
            "height": 2366.366366366366
        },
        "labels": {
            "labelName": "unnamed",
            "labelColor": "red",
            "labelColorRGB": "255,0,0",
            "visibility": false
        },
        "labelLocation": {
            "x": 1761.261261261261,
            "y": 2402.402402402402
        },
        "contentType": "polygon"
    },
    {
        "content": [
            {
                "x": 2085.5855855855852,
                "y": 1165.165165165165
            },
            {
                "x": 2451.9519519519517,
                "y": 1177.177177177177
            },
            {
                "x": 2151.6516516516517,
                "y": 3609.6096096096094
            },
            {
                "x": 1821.3213213213212,
                "y": 3627.6276276276276
            }
        ],
        "rectMask": {
            "xMin": 1821.3213213213212,
            "yMin": 1165.165165165165,
            "width": 630.6306306306305,
            "height": 2462.4624624624626
        },
        "labels": {
            "labelName": "unnamed",
            "labelColor": "red",
            "labelColorRGB": "255,0,0",
            "visibility": false
        },
        "labelLocation": {
            "x": 2136.6366366366365,
            "y": 2396.396396396396
        },
        "contentType": "polygon"
    },
    {
        "content": [
            {
                "x": 2469.96996996997,
                "y": 1129.129129129129
            },
            {
                "x": 2734.234234234234,
                "y": 1141.1411411411411
            },
            {
                "x": 2385.8858858858857,
                "y": 3555.555555555555
            },
            {
                "x": 2157.6576576576576,
                "y": 3573.5735735735734
            }
        ],
        "rectMask": {
            "xMin": 2157.6576576576576,
            "yMin": 1129.129129129129,
            "width": 576.5765765765766,
            "height": 2444.4444444444443
        },
        "labels": {
            "labelName": "unnamed",
            "labelColor": "red",
            "labelColorRGB": "255,0,0",
            "visibility": false
        },
        "labelLocation": {
            "x": 2445.945945945946,
            "y": 2351.3513513513512
        },
        "contentType": "polygon"
    },
    {
        "content": [
            {
                "x": 2770.27027027027,
                "y": 1111.111111111111
            },
            {
                "x": 2998.4984984984985,
                "y": 1129.129129129129
            },
            {
                "x": 3000,
                "y": 1477.4774774774774
            },
            {
                "x": 2674.174174174174,
                "y": 3567.5675675675675
            },
            {
                "x": 2445.945945945946,
                "y": 3555.555555555555
            }
        ],
        "rectMask": {
            "xMin": 2445.945945945946,
            "yMin": 1111.111111111111,
            "width": 554.0540540540541,
            "height": 2456.456456456456
        },
        "labels": {
            "labelName": "unnamed",
            "labelColor": "red",
            "labelColorRGB": "255,0,0",
            "visibility": false
        },
        "labelLocation": {
            "x": 2722.972972972973,
            "y": 2339.339339339339
        },
        "contentType": "polygon"
    }
]