[
    {
        "content": [
            {
                "x": 3117.2945205479455,
                "y": 15.41095890410959
            },
            {
                "x": 3533.3904109589043,
                "y": 0
            },
            {
                "x": 2793.6643835616437,
                "y": 2964.0410958904113
            },
            {
                "x": 2547.089041095891,
                "y": 2948.6301369863017
            }
        ],
        "rectMask": {
            "xMin": 2547.089041095891,
            "yMin": 0,
            "width": 986.3013698630137,
            "height": 2964.0410958904113
        },
        "labels": {
            "labelName": "unnamed",
            "labelColor": "red",
            "labelColorRGB": "255,0,0",
            "visibility": false
        },
        "labelLocation": {
            "x": 3040.239726027398,
            "y": 1482.0205479452056
        },
        "contentType": "polygon"
    },
    {
        "content": [
            {
                "x": 2742.294520547945,
                "y": 5.136986301369864
            },
            {
                "x": 3060.787671232877,
                "y": 15.41095890410959
            },
            {
                "x": 2547.089041095891,
                "y": 2876.7123287671234
            },
            {
                "x": 2274.828767123288,
                "y": 2902.3972602739727
            }
        ],
        "rectMask": {
            "xMin": 2274.828767123288,
            "yMin": 5.136986301369864,
            "width": 785.9589041095891,
            "height": 2897.260273972603
        },
        "labels": {
            "labelName": "unnamed",
            "labelColor": "red",
            "labelColorRGB": "255,0,0",
            "visibility": false
        },
        "labelLocation": {
            "x": 2667.8082191780823,
            "y": 1453.7671232876714
        },
        "contentType": "polygon"
    },
    {
        "content": [
            {
                "x": 2341.609589041096,
                "y": 20.547945205479454
            },
            {
                "x": 2721.7465753424653,
                "y": 10.273972602739727
            },
            {
                "x": 2238.869863013699,
                "y": 2907.5342465753424
            },
            {
                "x": 1992.2945205479455,
                "y": 2897.260273972603
            }
        ],
        "rectMask": {
            "xMin": 1992.2945205479455,
            "yMin": 10.273972602739727,
            "width": 729.4520547945206,
            "height": 2897.260273972603
        },
        "labels": {
            "labelName": "unnamed",
            "labelColor": "red",
            "labelColorRGB": "255,0,0",
            "visibility": false
        },
        "labelLocation": {
            "x": 2357.0205479452056,
            "y": 1458.9041095890414
        },
        "contentType": "polygon"
    },
    {
        "content": [
            {
                "x": 2002.5684931506853,
                "y": 35.95890410958904
            },
            {
                "x": 2341.609589041096,
                "y": 51.369863013698634
            },
            {
                "x": 1956.3356164383565,
                "y": 2804.7945205479455
            },
            {
                "x": 1699.4863013698632,
                "y": 2799.6575342465753
            }
        ],
        "rectMask": {
            "xMin": 1699.4863013698632,
            "yMin": 35.95890410958904,
            "width": 642.1232876712329,
            "height": 2768.8356164383563
        },
        "labels": {
            "labelName": "unnamed",
            "labelColor": "red",
            "labelColorRGB": "255,0,0",
            "visibility": false
        },
        "labelLocation": {
            "x": 2020.5479452054797,
            "y": 1420.376712328767
        },
        "contentType": "polygon"
    },
    {
        "content": [
            {
                "x": 1632.705479452055,
                "y": 51.369863013698634
            },
            {
                "x": 1997.4315068493154,
                "y": 87.32876712328768
            },
            {
                "x": 1663.5273972602743,
                "y": 2851.027397260274
            },
            {
                "x": 1442.6369863013701,
                "y": 2851.027397260274
            }
        ],
        "rectMask": {
            "xMin": 1442.6369863013701,
            "yMin": 51.369863013698634,
            "width": 554.7945205479452,
            "height": 2799.6575342465753
        },
        "labels": {
            "labelName": "unnamed",
            "labelColor": "red",
            "labelColorRGB": "255,0,0",
            "visibility": false
        },
        "labelLocation": {
            "x": 1720.0342465753429,
            "y": 1451.1986301369864
        },
        "contentType": "polygon"
    },
    {
        "content": [
            {
                "x": 2598.458904109589,
                "y": 2928.082191780822
            }
        ],
        "rectMask": {
            "xMin": null,
            "yMin": null,
            "width": null,
            "height": null
        },
        "labels": {
            "labelName": "unnamed",
            "labelColor": "red",
            "labelColorRGB": "255,0,0",
            "visibility": false
        },
        "labelLocation": {
            "x": null,
            "y": null
        },
        "contentType": "polygon"
    },
    {
        "content": [
            {
                "x": 1478.595890410959,
                "y": 107.87671232876713
            },
            {
                "x": 1632.705479452055,
                "y": 138.6986301369863
            },
            {
                "x": 1452.91095890411,
                "y": 2820.205479452055
            },
            {
                "x": 1298.801369863014,
                "y": 2830.479452054795
            }
        ],
        "rectMask": {
            "xMin": 1298.801369863014,
            "yMin": 107.87671232876713,
            "width": 333.9041095890411,
            "height": 2722.6027397260277
        },
        "labels": {
            "labelName": "unnamed",
            "labelColor": "red",
            "labelColorRGB": "255,0,0",
            "visibility": false
        },
        "labelLocation": {
            "x": 1465.7534246575347,
            "y": 1469.178082191781
        },
        "contentType": "polygon"
    },
    {
        "content": [
            {
                "x": 1273.116438356164,
                "y": 102.73972602739727
            },
            {
                "x": 1458.0479452054797,
                "y": 128.4246575342466
            },
            {
                "x": 1278.2534246575344,
                "y": 2825.3424657534247
            },
            {
                "x": 1160.102739726027,
                "y": 2840.753424657534
            }
        ],
        "rectMask": {
            "xMin": 1160.102739726027,
            "yMin": 102.73972602739727,
            "width": 297.94520547945206,
            "height": 2738.0136986301372
        },
        "labels": {
            "labelName": "unnamed",
            "labelColor": "red",
            "labelColorRGB": "255,0,0",
            "visibility": false
        },
        "labelLocation": {
            "x": 1309.075342465753,
            "y": 1471.7465753424658
        },
        "contentType": "polygon"
    },
    {
        "content": [
            {
                "x": 1119.0068493150688,
                "y": 138.6986301369863
            },
            {
                "x": 1273.116438356164,
                "y": 154.1095890410959
            },
            {
                "x": 1149.828767123288,
                "y": 2799.6575342465753
            },
            {
                "x": 1016.2671232876714,
                "y": 2804.7945205479455
            }
        ],
        "rectMask": {
            "xMin": 1016.2671232876714,
            "yMin": 138.6986301369863,
            "width": 256.8493150684932,
            "height": 2666.095890410959
        },
        "labels": {
            "labelName": "unnamed",
            "labelColor": "red",
            "labelColorRGB": "255,0,0",
            "visibility": false
        },
        "labelLocation": {
            "x": 1144.691780821918,
            "y": 1471.7465753424658
        },
        "contentType": "polygon"
    },
    {
        "content": [
            {
                "x": 898.1164383561646,
                "y": 123.28767123287672
            },
            {
                "x": 1098.4589041095894,
                "y": 164.38356164383563
            },
            {
                "x": 1011.1301369863016,
                "y": 2815.0684931506853
            },
            {
                "x": 877.5684931506852,
                "y": 2820.205479452055
            }
        ],
        "rectMask": {
            "xMin": 877.5684931506852,
            "yMin": 123.28767123287672,
            "width": 220.8904109589041,
            "height": 2696.9178082191784
        },
        "labels": {
            "labelName": "unnamed",
            "labelColor": "red",
            "labelColorRGB": "255,0,0",
            "visibility": false
        },
        "labelLocation": {
            "x": 988.0136986301372,
            "y": 1471.7465753424658
        },
        "contentType": "polygon"
    },
    {
        "content": [
            {
                "x": 713.1849315068496,
                "y": 128.4246575342466
            },
            {
                "x": 887.8424657534249,
                "y": 169.5205479452055
            },
            {
                "x": 872.4315068493153,
                "y": 2840.753424657534
            },
            {
                "x": 754.2808219178085,
                "y": 2851.027397260274
            }
        ],
        "rectMask": {
            "xMin": 713.1849315068496,
            "yMin": 128.4246575342466,
            "width": 174.65753424657535,
            "height": 2722.6027397260277
        },
        "labels": {
            "labelName": "unnamed",
            "labelColor": "red",
            "labelColorRGB": "255,0,0",
            "visibility": false
        },
        "labelLocation": {
            "x": 800.5136986301372,
            "y": 1489.7260273972604
        },
        "contentType": "polygon"
    },
    {
        "content": [
            {
                "x": 502.41615051548223,
                "y": 0
            },
            {
                "x": 784.9503970908247,
                "y": 34.83148722888131
            },
            {
                "x": 738.7175203784959,
                "y": 2788.2561447631283
            },
            {
                "x": 564.0599861319206,
                "y": 2819.0780625713473
            }
        ],
        "rectMask": {
            "xMin": 502.41615051548223,
            "yMin": 0,
            "width": 282.5342465753425,
            "height": 2819.0780625713473
        },
        "labels": {
            "labelName": "unnamed",
            "labelColor": "red",
            "labelColorRGB": "255,0,0",
            "visibility": false
        },
        "labelLocation": {
            "x": 643.6832738031535,
            "y": 1409.5390312856737
        },
        "contentType": "polygon"
    },
    {
        "content": [
            {
                "x": 189.05998613192057,
                "y": 4.0095694206621255
            },
            {
                "x": 502.41615051548223,
                "y": 29.69450092751144
            },
            {
                "x": 564.0599861319206,
                "y": 2844.7629940781967
            },
            {
                "x": 368.8545066798658,
                "y": 2870.447925585046
            }
        ],
        "rectMask": {
            "xMin": 189.05998613192057,
            "yMin": 4.0095694206621255,
            "width": 375,
            "height": 2866.4383561643835
        },
        "labels": {
            "labelName": "unnamed",
            "labelColor": "red",
            "labelColorRGB": "255,0,0",
            "visibility": false
        },
        "labelLocation": {
            "x": 376.5599861319206,
            "y": 1437.2287475028538
        },
        "contentType": "polygon"
    }
]