[
    {
        "content": [
            {
                "x": 41.388753255208144,
                "y": 595.2766927083331
            },
            {
                "x": 266.38875325520814,
                "y": 585.2766927083331
            },
            {
                "x": 421.38875325520814,
                "y": 2945.276692708333
            },
            {
                "x": 171.38875325520814,
                "y": 2895.276692708333
            }
        ],
        "rectMask": {
            "xMin": 41.388753255208144,
            "yMin": 585.2766927083331,
            "width": 380,
            "height": 2360
        },
        "labels": {
            "labelName": "unnamed",
            "labelColor": "red",
            "labelColorRGB": "255,0,0",
            "visibility": false
        },
        "labelLocation": {
            "x": 231.38875325520814,
            "y": 1765.276692708333
        },
        "contentType": "polygon"
    },
    {
        "content": [
            {
                "x": 246.38875325520814,
                "y": 345.27669270833314
            },
            {
                "x": 461.38875325520814,
                "y": 345.27669270833314
            },
            {
                "x": 596.3887532552081,
                "y": 2920.276692708333
            },
            {
                "x": 441.38875325520814,
                "y": 2920.276692708333
            }
        ],
        "rectMask": {
            "xMin": 246.38875325520814,
            "yMin": 345.27669270833314,
            "width": 350.00000000000006,
            "height": 2575
        },
        "labels": {
            "labelName": "unnamed",
            "labelColor": "red",
            "labelColorRGB": "255,0,0",
            "visibility": false
        },
        "labelLocation": {
            "x": 421.38875325520814,
            "y": 1632.776692708333
        },
        "contentType": "polygon"
    },
    {
        "content": [
            {
                "x": 471.38875325520814,
                "y": 405.2766927083332
            },
            {
                "x": 761.3887532552081,
                "y": 410.27669270833314
            },
            {
                "x": 861.3887532552081,
                "y": 2900.276692708333
            },
            {
                "x": 606.3887532552081,
                "y": 2915.276692708333
            }
        ],
        "rectMask": {
            "xMin": 471.38875325520814,
            "yMin": 405.2766927083332,
            "width": 390,
            "height": 2510
        },
        "labels": {
            "labelName": "unnamed",
            "labelColor": "red",
            "labelColorRGB": "255,0,0",
            "visibility": false
        },
        "labelLocation": {
            "x": 666.3887532552081,
            "y": 1660.2766927083333
        },
        "contentType": "polygon"
    },
    {
        "content": [
            {
                "x": 781.3887532552081,
                "y": 455.27669270833314
            },
            {
                "x": 1051.388753255208,
                "y": 445.27669270833314
            },
            {
                "x": 1106.388753255208,
                "y": 2895.276692708333
            },
            {
                "x": 881.3887532552081,
                "y": 2905.276692708333
            }
        ],
        "rectMask": {
            "xMin": 781.3887532552081,
            "yMin": 445.27669270833314,
            "width": 325,
            "height": 2460
        },
        "labels": {
            "labelName": "unnamed",
            "labelColor": "red",
            "labelColorRGB": "255,0,0",
            "visibility": false
        },
        "labelLocation": {
            "x": 943.8887532552081,
            "y": 1675.276692708333
        },
        "contentType": "polygon"
    },
    {
        "content": [
            {
                "x": 1061.388753255208,
                "y": 435.27669270833314
            },
            {
                "x": 1336.3887532552083,
                "y": 430.27669270833314
            },
            {
                "x": 1366.388753255208,
                "y": 2935.276692708333
            },
            {
                "x": 1106.388753255208,
                "y": 2925.276692708333
            }
        ],
        "rectMask": {
            "xMin": 1061.388753255208,
            "yMin": 430.27669270833314,
            "width": 305,
            "height": 2505
        },
        "labels": {
            "labelName": "unnamed",
            "labelColor": "red",
            "labelColorRGB": "255,0,0",
            "visibility": false
        },
        "labelLocation": {
            "x": 1213.888753255208,
            "y": 1682.776692708333
        },
        "contentType": "polygon"
    },
    {
        "content": [
            {
                "x": 1351.388753255208,
                "y": 360.2766927083332
            },
            {
                "x": 1486.388753255208,
                "y": 355.27669270833303
            },
            {
                "x": 1491.3887532552078,
                "y": 2935.276692708333
            },
            {
                "x": 1371.388753255208,
                "y": 2945.276692708333
            }
        ],
        "rectMask": {
            "xMin": 1351.388753255208,
            "yMin": 355.27669270833303,
            "width": 140,
            "height": 2590
        },
        "labels": {
            "labelName": "unnamed",
            "labelColor": "red",
            "labelColorRGB": "255,0,0",
            "visibility": false
        },
        "labelLocation": {
            "x": 1421.388753255208,
            "y": 1650.276692708333
        },
        "contentType": "polygon"
    },
    {
        "content": [
            {
                "x": 1481.388753255208,
                "y": 345.27669270833314
            },
            {
                "x": 1851.388753255208,
                "y": 375.27669270833314
            },
            {
                "x": 1791.388753255208,
                "y": 2945.276692708333
            },
            {
                "x": 1491.3887532552078,
                "y": 2935.276692708333
            }
        ],
        "rectMask": {
            "xMin": 1481.388753255208,
            "yMin": 345.27669270833314,
            "width": 370,
            "height": 2600
        },
        "labels": {
            "labelName": "unnamed",
            "labelColor": "red",
            "labelColorRGB": "255,0,0",
            "visibility": false
        },
        "labelLocation": {
            "x": 1666.388753255208,
            "y": 1645.276692708333
        },
        "contentType": "polygon"
    },
    {
        "content": [
            {
                "x": 1871.3887532552078,
                "y": 455.27669270833314
            },
            {
                "x": 2131.388753255208,
                "y": 435.27669270833314
            },
            {
                "x": 2051.388753255208,
                "y": 2925.276692708333
            },
            {
                "x": 1801.388753255208,
                "y": 2925.276692708333
            }
        ],
        "rectMask": {
            "xMin": 1801.388753255208,
            "yMin": 435.27669270833314,
            "width": 330,
            "height": 2490
        },
        "labels": {
            "labelName": "unnamed",
            "labelColor": "red",
            "labelColorRGB": "255,0,0",
            "visibility": false
        },
        "labelLocation": {
            "x": 1966.388753255208,
            "y": 1680.276692708333
        },
        "contentType": "polygon"
    },
    {
        "content": [
            {
                "x": 2191.388753255208,
                "y": 510.27669270833314
            },
            {
                "x": 2441.388753255208,
                "y": 515.2766927083331
            },
            {
                "x": 2341.3887532552085,
                "y": 2905.276692708333
            },
            {
                "x": 2101.388753255208,
                "y": 2945.276692708333
            }
        ],
        "rectMask": {
            "xMin": 2101.388753255208,
            "yMin": 510.27669270833314,
            "width": 340,
            "height": 2435
        },
        "labels": {
            "labelName": "unnamed",
            "labelColor": "red",
            "labelColorRGB": "255,0,0",
            "visibility": false
        },
        "labelLocation": {
            "x": 2271.388753255208,
            "y": 1727.776692708333
        },
        "contentType": "polygon"
    },
    {
        "content": [
            {
                "x": 2481.6971713810317,
                "y": 384.3594009983361
            },
            {
                "x": 2791.1813643926794,
                "y": 399.33444259567386
            },
            {
                "x": 2611.480865224626,
                "y": 2945.0915141430946
            },
            {
                "x": 2351.9134775374378,
                "y": 2945.0915141430946
            }
        ],
        "rectMask": {
            "xMin": 2351.9134775374378,
            "yMin": 384.3594009983361,
            "width": 439.2678868552413,
            "height": 2560.732113144759
        },
        "labels": {
            "labelName": "unnamed",
            "labelColor": "red",
            "labelColorRGB": "255,0,0",
            "visibility": false
        },
        "labelLocation": {
            "x": 2571.5474209650583,
            "y": 1664.7254575707157
        },
        "contentType": "polygon"
    },
    {
        "content": [
            {
                "x": 2826.1231281198006,
                "y": 319.4675540765391
            },
            {
                "x": 3290.3494176372715,
                "y": 319.4675540765391
            },
            {
                "x": 3011.156405990017,
                "y": 2996.7054908485857
            },
            {
                "x": 2621.156405990017,
                "y": 2956.7054908485857
            }
        ],
        "rectMask": {
            "xMin": 2621.156405990017,
            "yMin": 319.4675540765391,
            "width": 669.1930116472543,
            "height": 2677.2379367720464
        },
        "labels": {
            "labelName": "unnamed",
            "labelColor": "red",
            "labelColorRGB": "255,0,0",
            "visibility": false
        },
        "labelLocation": {
            "x": 2955.752911813644,
            "y": 1658.0865224625622
        },
        "contentType": "polygon"
    },
    {
        "content": [
            {
                "x": 3301.156405990017,
                "y": 276.7054908485858
            },
            {
                "x": 3521.156405990017,
                "y": 301.7054908485858
            },
            {
                "x": 3201.156405990017,
                "y": 2986.7054908485857
            },
            {
                "x": 3031.156405990017,
                "y": 2976.7054908485857
            }
        ],
        "rectMask": {
            "xMin": 3031.156405990017,
            "yMin": 276.7054908485858,
            "width": 490,
            "height": 2710
        },
        "labels": {
            "labelName": "unnamed",
            "labelColor": "red",
            "labelColorRGB": "255,0,0",
            "visibility": false
        },
        "labelLocation": {
            "x": 3276.156405990017,
            "y": 1631.7054908485857
        },
        "contentType": "polygon"
    },
    {
        "content": [
            {
                "x": 3521.156405990017,
                "y": 271.7054908485858
            },
            {
                "x": 3771.156405990017,
                "y": 261.7054908485858
            },
            {
                "x": 3481.156405990017,
                "y": 2981.7054908485857
            },
            {
                "x": 3251.156405990017,
                "y": 2976.7054908485857
            }
        ],
        "rectMask": {
            "xMin": 3251.156405990017,
            "yMin": 261.7054908485858,
            "width": 520,
            "height": 2720
        },
        "labels": {
            "labelName": "unnamed",
            "labelColor": "red",
            "labelColorRGB": "255,0,0",
            "visibility": false
        },
        "labelLocation": {
            "x": 3511.156405990017,
            "y": 1621.7054908485857
        },
        "contentType": "polygon"
    }
]