[
    {
        "content": [
            {
                "x": 20.694610778443113,
                "y": 1206.4311377245508
            },
            {
                "x": 4014.7544910179636,
                "y": 1147.7964071856286
            },
            {
                "x": 4025.1017964071852,
                "y": 1527.197604790419
            },
            {
                "x": 3.4491017964071853,
                "y": 1647.9161676646704
            }
        ],
        "rectMask": {
            "xMin": 3.4491017964071853,
            "yMin": 1147.7964071856286,
            "width": 4021.6526946107783,
            "height": 500.1197604790419
        },
        "labels": {
            "labelName": "unnamed",
            "labelColor": "red",
            "labelColorRGB": "255,0,0",
            "visibility": false
        },
        "labelLocation": {
            "x": 2014.2754491017963,
            "y": 1397.8562874251495
        },
        "contentType": "polygon"
    }
]