[
    {
        "content": [
            {
                "x": 13.796407185628741,
                "y": 833.9281437125748
            },
            {
                "x": 3524.9820359281434,
                "y": 764.9461077844311
            },
            {
                "x": 3493.940119760479,
                "y": 1054.6706586826347
            },
            {
                "x": 10.347305389221557,
                "y": 1316.8023952095807
            }
        ],
        "rectMask": {
            "xMin": 10.347305389221557,
            "yMin": 764.9461077844311,
            "width": 3514.6347305389218,
            "height": 551.8562874251496
        },
        "labels": {
            "labelName": "unnamed",
            "labelColor": "red",
            "labelColorRGB": "255,0,0",
            "visibility": false
        },
        "labelLocation": {
            "x": 1767.6646706586823,
            "y": 1040.8742514970058
        },
        "contentType": "polygon"
    }
]