[
    {
        "content": [
            {
                "x": 338.49557522123894,
                "y": 1725.6637168141592
            },
            {
                "x": 3409.29203539823,
                "y": 1376.1061946902655
            },
            {
                "x": 3378.3185840707965,
                "y": 1592.9203539823009
            },
            {
                "x": 365.04424778761063,
                "y": 2075.221238938053
            }
        ],
        "rectMask": {
            "xMin": 338.49557522123894,
            "yMin": 1376.1061946902655,
            "width": 3070.796460176991,
            "height": 699.1150442477876
        },
        "labels": {
            "labelName": "unnamed",
            "labelColor": "red",
            "labelColorRGB": "255,0,0",
            "visibility": false
        },
        "labelLocation": {
            "x": 1873.8938053097345,
            "y": 1725.6637168141592
        },
        "contentType": "polygon"
    }
]