[
    {
        "content": [
            {
                "x": 307.5221238938053,
                "y": 1353.9823008849557
            },
            {
                "x": 3838.495575221239,
                "y": 1526.5486725663716
            },
            {
                "x": 3776.5486725663714,
                "y": 2141.592920353982
            },
            {
                "x": 338.49557522123894,
                "y": 1929.203539823009
            }
        ],
        "rectMask": {
            "xMin": 307.5221238938053,
            "yMin": 1353.9823008849557,
            "width": 3530.9734513274334,
            "height": 787.6106194690266
        },
        "labels": {
            "labelName": "unnamed",
            "labelColor": "red",
            "labelColorRGB": "255,0,0",
            "visibility": false
        },
        "labelLocation": {
            "x": 2073.008849557522,
            "y": 1747.787610619469
        },
        "contentType": "polygon"
    }
]