[
    {
        "content": [
            {
                "x": 0,
                "y": 84.14769776114748
            },
            {
                "x": 212.3344253163436,
                "y": 87.73344951261036
            },
            {
                "x": 570.9096004626324,
                "y": 2156.7122101066966
            },
            {
                "x": 377.27900588363644,
                "y": 2171.0552171125482
            }
        ],
        "rectMask": {
            "xMin": 0,
            "yMin": 84.14769776114748,
            "width": 570.9096004626324,
            "height": 2086.9075193514004
        },
        "labels": {
            "labelName": "unnamed",
            "labelColor": "red",
            "labelColorRGB": "255,0,0",
            "visibility": false
        },
        "labelLocation": {
            "x": 285.4548002313162,
            "y": 1127.6014574368478
        },
        "contentType": "polygon"
    },
    {
        "content": [
            {
                "x": 233.84893582512095,
                "y": 80.56194600968459
            },
            {
                "x": 434.65103390704263,
                "y": 76.97619425822171
            },
            {
                "x": 786.0547055504056,
                "y": 2142.369203100845
            },
            {
                "x": 603.1813662257983,
                "y": 2163.883713609622
            }
        ],
        "rectMask": {
            "xMin": 233.84893582512095,
            "yMin": 76.97619425822171,
            "width": 552.2057697252847,
            "height": 2086.9075193514004
        },
        "labels": {
            "labelName": "unnamed",
            "labelColor": "red",
            "labelColorRGB": "255,0,0",
            "visibility": false
        },
        "labelLocation": {
            "x": 509.9518206877633,
            "y": 1120.429953933922
        },
        "contentType": "polygon"
    },
    {
        "content": [
            {
                "x": 441.82253740996845,
                "y": 80.56194600968459
            },
            {
                "x": 664.1391460006674,
                "y": 76.97619425822171
            },
            {
                "x": 1004.7855623896418,
                "y": 2156.7122101066966
            },
            {
                "x": 803.98346430772,
                "y": 2174.640968864011
            }
        ],
        "rectMask": {
            "xMin": 441.82253740996845,
            "yMin": 76.97619425822171,
            "width": 562.9630249796734,
            "height": 2097.6647746057893
        },
        "labels": {
            "labelName": "unnamed",
            "labelColor": "red",
            "labelColorRGB": "255,0,0",
            "visibility": false
        },
        "labelLocation": {
            "x": 723.3040498998051,
            "y": 1125.8085815611164
        },
        "contentType": "polygon"
    },
    {
        "content": [
            {
                "x": 682.0679047579819,
                "y": 80.56194600968459
            },
            {
                "x": 893.6272580942923,
                "y": 73.39044250675882
            },
            {
                "x": 1202.0019087201006,
                "y": 2156.7122101066966
            },
            {
                "x": 1015.5428176440304,
                "y": 2171.0552171125482
            }
        ],
        "rectMask": {
            "xMin": 682.0679047579819,
            "yMin": 73.39044250675882,
            "width": 519.9340039621187,
            "height": 2097.6647746057893
        },
        "labels": {
            "labelName": "unnamed",
            "labelColor": "red",
            "labelColorRGB": "255,0,0",
            "visibility": false
        },
        "labelLocation": {
            "x": 942.0349067390412,
            "y": 1122.2228298096534
        },
        "contentType": "polygon"
    },
    {
        "content": [
            {
                "x": 911.5560168516067,
                "y": 76.97619425822171
            },
            {
                "x": 1133.8726254423057,
                "y": 87.73344951261036
            },
            {
                "x": 1402.8040068020223,
                "y": 2153.126458355234
            },
            {
                "x": 1212.7591639744892,
                "y": 2174.640968864011
            }
        ],
        "rectMask": {
            "xMin": 911.5560168516067,
            "yMin": 76.97619425822171,
            "width": 491.2479899504156,
            "height": 2097.6647746057893
        },
        "labels": {
            "labelName": "unnamed",
            "labelColor": "red",
            "labelColorRGB": "255,0,0",
            "visibility": false
        },
        "labelLocation": {
            "x": 1157.1800118268145,
            "y": 1125.8085815611164
        },
        "contentType": "polygon"
    },
    {
        "content": [
            {
                "x": 1169.7301429569345,
                "y": 76.97619425822171
            },
            {
                "x": 1366.9464892873934,
                "y": 76.97619425822171
            },
            {
                "x": 1596.4346013810182,
                "y": 2142.369203100845
            },
            {
                "x": 1413.561262056411,
                "y": 2160.2979618581594
            }
        ],
        "rectMask": {
            "xMin": 1169.7301429569345,
            "yMin": 76.97619425822171,
            "width": 426.7044584240836,
            "height": 2083.3217675999376
        },
        "labels": {
            "labelName": "unnamed",
            "labelColor": "red",
            "labelColorRGB": "255,0,0",
            "visibility": false
        },
        "labelLocation": {
            "x": 1383.0823721689762,
            "y": 1118.6370780581906
        },
        "contentType": "polygon"
    },
    {
        "content": [
            {
                "x": 1409.975510304948,
                "y": 66.21893900383304
            },
            {
                "x": 1621.5348636412584,
                "y": 69.80469075529592
            },
            {
                "x": 1790.065195960014,
                "y": 2145.9549548523078
            },
            {
                "x": 1607.1918566354068,
                "y": 2156.7122101066966
            }
        ],
        "rectMask": {
            "xMin": 1409.975510304948,
            "yMin": 66.21893900383304,
            "width": 380.0896856550661,
            "height": 2090.493271102863
        },
        "labels": {
            "labelName": "unnamed",
            "labelColor": "red",
            "labelColorRGB": "255,0,0",
            "visibility": false
        },
        "labelLocation": {
            "x": 1600.0203531324812,
            "y": 1111.4655745552645
        },
        "contentType": "polygon"
    },
    {
        "content": [
            {
                "x": 1660.9781329073503,
                "y": 62.633187252370156
            },
            {
                "x": 1861.7802309892718,
                "y": 59.04743550090727
            },
            {
                "x": 1994.4530457933986,
                "y": 2153.126458355234
            },
            {
                "x": 1818.7512099717173,
                "y": 2153.126458355234
            }
        ],
        "rectMask": {
            "xMin": 1660.9781329073503,
            "yMin": 59.04743550090727,
            "width": 333.4749128860485,
            "height": 2094.0790228543265
        },
        "labels": {
            "labelName": "unnamed",
            "labelColor": "red",
            "labelColorRGB": "255,0,0",
            "visibility": false
        },
        "labelLocation": {
            "x": 1827.7155893503746,
            "y": 1106.0869469280706
        },
        "contentType": "polygon"
    },
    {
        "content": [
            {
                "x": 1890.4662450009748,
                "y": 62.633187252370156
            },
            {
                "x": 2098.439846585822,
                "y": 73.39044250675882
            },
            {
                "x": 2177.326385118006,
                "y": 2149.540706603771
            },
            {
                "x": 2005.2103010477872,
                "y": 2171.0552171125482
            }
        ],
        "rectMask": {
            "xMin": 1890.4662450009748,
            "yMin": 62.633187252370156,
            "width": 286.860140117031,
            "height": 2108.422029860178
        },
        "labels": {
            "labelName": "unnamed",
            "labelColor": "red",
            "labelColorRGB": "255,0,0",
            "visibility": false
        },
        "labelLocation": {
            "x": 2033.8963150594902,
            "y": 1116.8442021824592
        },
        "contentType": "polygon"
    },
    {
        "content": [
            {
                "x": 2134.297364100451,
                "y": 59.04743550090727
            },
            {
                "x": 2342.2709656852985,
                "y": 55.461683749444376
            },
            {
                "x": 2363.7854761940757,
                "y": 2153.126458355234
            },
            {
                "x": 2198.840895626783,
                "y": 2163.883713609622
            }
        ],
        "rectMask": {
            "xMin": 2134.297364100451,
            "yMin": 55.461683749444376,
            "width": 229.4881120936248,
            "height": 2108.422029860178
        },
        "labels": {
            "labelName": "unnamed",
            "labelColor": "red",
            "labelColorRGB": "255,0,0",
            "visibility": false
        },
        "labelLocation": {
            "x": 2249.0414201472636,
            "y": 1109.6726986795334
        },
        "contentType": "polygon"
    },
    {
        "content": [
            {
                "x": 2378.1284831999274,
                "y": 66.21893900383304
            },
            {
                "x": 2575.3448295303865,
                "y": 62.633187252370156
            },
            {
                "x": 2550.244567270146,
                "y": 2149.540706603771
            },
            {
                "x": 2381.7142349513906,
                "y": 2163.883713609622
            }
        ],
        "rectMask": {
            "xMin": 2378.1284831999274,
            "yMin": 62.633187252370156,
            "width": 197.2163463304588,
            "height": 2101.250526357252
        },
        "labels": {
            "labelName": "unnamed",
            "labelColor": "red",
            "labelColorRGB": "255,0,0",
            "visibility": false
        },
        "labelLocation": {
            "x": 2476.7366563651567,
            "y": 1113.2584504309962
        },
        "contentType": "polygon"
    },
    {
        "content": [
            {
                "x": 2600.4450917906265,
                "y": 55.461683749444376
            },
            {
                "x": 2808.418693375474,
                "y": 62.633187252370156
            },
            {
                "x": 2740.289410097679,
                "y": 2142.369203100845
            },
            {
                "x": 2571.7590777789233,
                "y": 2145.9549548523078
            }
        ],
        "rectMask": {
            "xMin": 2571.7590777789233,
            "yMin": 55.461683749444376,
            "width": 236.65961559655057,
            "height": 2090.493271102863
        },
        "labels": {
            "labelName": "unnamed",
            "labelColor": "red",
            "labelColorRGB": "255,0,0",
            "visibility": false
        },
        "labelLocation": {
            "x": 2690.0888855771987,
            "y": 1100.708319300876
        },
        "contentType": "polygon"
    },
    {
        "content": [
            {
                "x": 2847.8619626415657,
                "y": 44.704428495055716
            },
            {
                "x": 3037.906805469099,
                "y": 62.633187252370156
            },
            {
                "x": 2915.9912459193606,
                "y": 2142.369203100845
            },
            {
                "x": 2758.2181688549936,
                "y": 2135.1976995979194
            }
        ],
        "rectMask": {
            "xMin": 2758.2181688549936,
            "yMin": 44.704428495055716,
            "width": 279.68863661410523,
            "height": 2097.6647746057893
        },
        "labels": {
            "labelName": "unnamed",
            "labelColor": "red",
            "labelColorRGB": "255,0,0",
            "visibility": false
        },
        "labelLocation": {
            "x": 2898.062487162046,
            "y": 1093.5368157979503
        },
        "contentType": "polygon"
    },
    {
        "content": [
            {
                "x": 3080.9358264866532,
                "y": 44.704428495055716
            },
            {
                "x": 2937.505756428138,
                "y": 2142.369203100845
            },
            {
                "x": 3123.964847504208,
                "y": 2145.9549548523078
            },
            {
                "x": 3278.1521728171124,
                "y": 44.704428495055716
            }
        ],
        "rectMask": {
            "xMin": 2937.505756428138,
            "yMin": 44.704428495055716,
            "width": 340.64641638897433,
            "height": 2101.250526357252
        },
        "labels": {
            "labelName": "unnamed",
            "labelColor": "red",
            "labelColorRGB": "255,0,0",
            "visibility": false
        },
        "labelLocation": {
            "x": 3107.828964622625,
            "y": 1095.3296916736817
        },
        "contentType": "polygon"
    },
    {
        "content": [
            {
                "x": 3335.5242008405185,
                "y": 41.11867674359283
            },
            {
                "x": 3138.3078545100598,
                "y": 2138.783451349382
            },
            {
                "x": 3317.595442083204,
                "y": 2153.126458355234
            },
            {
                "x": 3543.497802425366,
                "y": 51.87593199798149
            }
        ],
        "rectMask": {
            "xMin": 3138.3078545100598,
            "yMin": 41.11867674359283,
            "width": 405.1899479153063,
            "height": 2112.007781611641
        },
        "labels": {
            "labelName": "unnamed",
            "labelColor": "red",
            "labelColorRGB": "255,0,0",
            "visibility": false
        },
        "labelLocation": {
            "x": 3340.902828467713,
            "y": 1097.1225675494134
        },
        "contentType": "polygon"
    },
    {
        "content": [
            {
                "x": 3568.598064685606,
                "y": 44.704428495055716
            },
            {
                "x": 3324.7669455861296,
                "y": 2142.369203100845
            },
            {
                "x": 3493.2972779048855,
                "y": 2131.611947846456
            },
            {
                "x": 3762.228659264602,
                "y": 55.461683749444376
            }
        ],
        "rectMask": {
            "xMin": 3324.7669455861296,
            "yMin": 44.704428495055716,
            "width": 437.4617136784723,
            "height": 2097.6647746057893
        },
        "labels": {
            "labelName": "unnamed",
            "labelColor": "red",
            "labelColorRGB": "255,0,0",
            "visibility": false
        },
        "labelLocation": {
            "x": 3543.497802425366,
            "y": 1093.5368157979503
        },
        "contentType": "polygon"
    },
    {
        "content": [
            {
                "x": 3790.914673276305,
                "y": 41.11867674359283
            },
            {
                "x": 3959.445005595061,
                "y": 41.11867674359283
            },
            {
                "x": 3672.5848654780298,
                "y": 2110.097437337679
            },
            {
                "x": 3507.640284910737,
                "y": 2128.0261960949933
            }
        ],
        "rectMask": {
            "xMin": 3507.640284910737,
            "yMin": 41.11867674359283,
            "width": 451.80472068432385,
            "height": 2086.9075193514004
        },
        "labels": {
            "labelName": "unnamed",
            "labelColor": "red",
            "labelColorRGB": "255,0,0",
            "visibility": false
        },
        "labelLocation": {
            "x": 3733.542645252899,
            "y": 1084.5724364192931
        },
        "contentType": "polygon"
    }
]